{
  "last_node_id": 20,
  "last_link_id": 21,
  "nodes": [
    {
      "id": 8,
      "type": "VAEDecode",
      "pos": {
        "0": 1209,
        "1": 188
      },
      "size": {
        "0": 210,
        "1": 46
      },
      "flags": {},
      "order": 12,
      "mode": 0,
      "inputs": [
        {
          "name": "samples",
          "type": "LATENT",
          "link": 7,
          "label": "Latent"
        },
        {
          "name": "vae",
          "type": "VAE",
          "link": 15,
          "label": "VAE"
        }
      ],
      "outputs": [
        {
          "name": "IMAGE",
          "type": "IMAGE",
          "links": [
            9
          ],
          "slot_index": 0,
          "label": "图像"
        }
      ],
      "properties": {
        "Node name for S&R": "VAEDecode"
      }
    },
    {
      "id": 5,
      "type": "EmptyLatentImage",
      "pos": {
        "0": 473,
        "1": 609
      },
      "size": {
        "0": 315,
        "1": 106
      },
      "flags": {},
      "order": 0,
      "mode": 0,
      "inputs": [],
      "outputs": [
        {
          "name": "LATENT",
          "type": "LATENT",
          "links": [
            2
          ],
          "slot_index": 0,
          "label": "Latent"
        }
      ],
      "properties": {
        "Node name for S&R": "EmptyLatentImage"
      },
      "widgets_values": [
        1024,
        1024,
        1
      ]
    },
    {
      "id": 9,
      "type": "SaveImage",
      "pos": {
        "0": 1451,
        "1": 189
      },
      "size": {
        "0": 429.91778564453125,
        "1": 478.2488708496094
      },
      "flags": {},
      "order": 13,
      "mode": 0,
      "inputs": [
        {
          "name": "images",
          "type": "IMAGE",
          "link": 9,
          "label": "图像"
        }
      ],
      "outputs": [],
      "properties": {
        "Node name for S&R": "SaveImage"
      },
      "widgets_values": [
        "ComfyUI"
      ]
    },
    {
      "id": 14,
      "type": "DualCLIPLoaderGGUF",
      "pos": {
        "0": 52,
        "1": 323
      },
      "size": {
        "0": 315,
        "1": 106
      },
      "flags": {},
      "order": 1,
      "mode": 0,
      "inputs": [],
      "outputs": [
        {
          "name": "CLIP",
          "type": "CLIP",
          "links": [
            13,
            14
          ],
          "slot_index": 0,
          "shape": 3,
          "label": "CLIP"
        }
      ],
      "properties": {
        "Node name for S&R": "DualCLIPLoaderGGUF"
      },
      "widgets_values": [
        "t5xxl_fp8_e4m3fn.safetensors",
        "clip_l.safetensors",
        "flux"
      ]
    },
    {
      "id": 15,
      "type": "VAELoader",
      "pos": {
        "0": 57,
        "1": 505
      },
      "size": {
        "0": 315,
        "1": 58
      },
      "flags": {},
      "order": 2,
      "mode": 0,
      "inputs": [],
      "outputs": [
        {
          "name": "VAE",
          "type": "VAE",
          "links": [
            15
          ],
          "shape": 3
        }
      ],
      "properties": {
        "Node name for S&R": "VAELoader"
      },
      "widgets_values": [
        "ae.sft"
      ]
    },
    {
      "id": 7,
      "type": "CLIPTextEncode",
      "pos": {
        "0": 411,
        "1": 397
      },
      "size": {
        "0": 425.27801513671875,
        "1": 180.6060791015625
      },
      "flags": {},
      "order": 9,
      "mode": 0,
      "inputs": [
        {
          "name": "clip",
          "type": "CLIP",
          "link": 14,
          "label": "CLIP"
        }
      ],
      "outputs": [
        {
          "name": "CONDITIONING",
          "type": "CONDITIONING",
          "links": [
            6
          ],
          "slot_index": 0,
          "label": "条件"
        }
      ],
      "properties": {
        "Node name for S&R": "CLIPTextEncode"
      },
      "widgets_values": [
        "text, watermark",
        true
      ]
    },
    {
      "id": 10,
      "type": "UnetLoaderGGUF",
      "pos": {
        "0": 54,
        "1": 189
      },
      "size": {
        "0": 315,
        "1": 58
      },
      "flags": {},
      "order": 3,
      "mode": 0,
      "inputs": [],
      "outputs": [
        {
          "name": "MODEL",
          "type": "MODEL",
          "links": [
            16
          ],
          "slot_index": 0,
          "shape": 3,
          "label": "MODEL"
        }
      ],
      "properties": {
        "Node name for S&R": "UnetLoaderGGUF"
      },
      "widgets_values": [
        "flux1-dev-Q8_0.gguf"
      ]
    },
    {
      "id": 17,
      "type": "PulidFluxModelLoader",
      "pos": {
        "0": 49.45099639892578,
        "1": -574.481201171875
      },
      "size": {
        "0": 315,
        "1": 58
      },
      "flags": {},
      "order": 4,
      "mode": 0,
      "inputs": [],
      "outputs": [
        {
          "name": "PULIDFLUX",
          "type": "PULIDFLUX",
          "links": [
            18
          ],
          "shape": 3,
          "label": "PULIDFLUX"
        }
      ],
      "properties": {
        "Node name for S&R": "PulidFluxModelLoader"
      },
      "widgets_values": [
        "pulid_flux_v0.9.0.safetensors"
      ]
    },
    {
      "id": 16,
      "type": "ApplyPulidFlux",
      "pos": {
        "0": 479.45098876953125,
        "1": -474.4812316894531
      },
      "size": {
        "0": 315,
        "1": 206
      },
      "flags": {},
      "order": 10,
      "mode": 0,
      "inputs": [
        {
          "name": "model",
          "type": "MODEL",
          "link": 16,
          "label": "model"
        },
        {
          "name": "pulid_flux",
          "type": "PULIDFLUX",
          "link": 18,
          "label": "pulid_flux"
        },
        {
          "name": "eva_clip",
          "type": "EVA_CLIP",
          "link": 19,
          "label": "eva_clip"
        },
        {
          "name": "face_analysis",
          "type": "FACEANALYSIS",
          "link": 20,
          "label": "face_analysis"
        },
        {
          "name": "image",
          "type": "IMAGE",
          "link": 21,
          "label": "image"
        },
        {
          "name": "attn_mask",
          "type": "MASK",
          "link": null,
          "label": "attn_mask"
        }
      ],
      "outputs": [
        {
          "name": "MODEL",
          "type": "MODEL",
          "links": [
            17
          ],
          "slot_index": 0,
          "shape": 3,
          "label": "MODEL"
        }
      ],
      "properties": {
        "Node name for S&R": "ApplyPulidFlux"
      },
      "widgets_values": [
        1,
        0,
        1
      ]
    },
    {
      "id": 19,
      "type": "PulidFluxInsightFaceLoader",
      "pos": {
        "0": 52.45099639892578,
        "1": -379.4812316894531
      },
      "size": {
        "0": 275.8501892089844,
        "1": 58
      },
      "flags": {},
      "order": 5,
      "mode": 0,
      "inputs": [],
      "outputs": [
        {
          "name": "FACEANALYSIS",
          "type": "FACEANALYSIS",
          "links": [
            20
          ],
          "shape": 3,
          "label": "FACEANALYSIS"
        }
      ],
      "properties": {
        "Node name for S&R": "PulidFluxInsightFaceLoader"
      },
      "widgets_values": [
        "CUDA"
      ]
    },
    {
      "id": 18,
      "type": "PulidFluxEvaClipLoader",
      "pos": {
        "0": 50.45099639892578,
        "1": -455.4812316894531
      },
      "size": {
        "0": 298.2184143066406,
        "1": 26
      },
      "flags": {},
      "order": 6,
      "mode": 0,
      "inputs": [],
      "outputs": [
        {
          "name": "EVA_CLIP",
          "type": "EVA_CLIP",
          "links": [
            19
          ],
          "shape": 3,
          "label": "EVA_CLIP"
        }
      ],
      "properties": {
        "Node name for S&R": "PulidFluxEvaClipLoader"
      }
    },
    {
      "id": 6,
      "type": "CLIPTextEncode",
      "pos": {
        "0": 414,
        "1": 190
      },
      "size": {
        "0": 422.84503173828125,
        "1": 164.31304931640625
      },
      "flags": {},
      "order": 8,
      "mode": 0,
      "inputs": [
        {
          "name": "clip",
          "type": "CLIP",
          "link": 13,
          "label": "CLIP"
        }
      ],
      "outputs": [
        {
          "name": "CONDITIONING",
          "type": "CONDITIONING",
          "links": [
            4
          ],
          "slot_index": 0,
          "label": "条件"
        }
      ],
      "properties": {
        "Node name for S&R": "CLIPTextEncode"
      },
      "widgets_values": [
        "A young woman wearing a flowing dress is lying gracefully on a bed of vibrant, blooming flowers. Her delicate figure is surrounded by colorful petals, with soft light filtering through the scene. The flowers include roses, lilies, and daisies in shades of red, pink, and white, creating a dreamy, serene atmosphere. The sunlight casts a warm, golden glow over her, highlighting the softness of her skin and the intricate details of her dress, as the scene exudes a peaceful, romantic aura.",
        true
      ]
    },
    {
      "id": 3,
      "type": "KSampler",
      "pos": {
        "0": 866,
        "1": 191
      },
      "size": {
        "0": 315,
        "1": 474
      },
      "flags": {},
      "order": 11,
      "mode": 0,
      "inputs": [
        {
          "name": "model",
          "type": "MODEL",
          "link": 17,
          "label": "模型"
        },
        {
          "name": "positive",
          "type": "CONDITIONING",
          "link": 4,
          "label": "正面条件"
        },
        {
          "name": "negative",
          "type": "CONDITIONING",
          "link": 6,
          "label": "负面条件"
        },
        {
          "name": "latent_image",
          "type": "LATENT",
          "link": 2,
          "label": "Latent"
        }
      ],
      "outputs": [
        {
          "name": "LATENT",
          "type": "LATENT",
          "links": [
            7
          ],
          "slot_index": 0,
          "label": "Latent"
        }
      ],
      "properties": {
        "Node name for S&R": "KSampler"
      },
      "widgets_values": [
        186462208016243,
        "fixed",
        20,
        1,
        "euler",
        "normal",
        1
      ]
    },
    {
      "id": 20,
      "type": "LoadImage",
      "pos": {
        "0": 53.45099639892578,
        "1": -259.4812316894531
      },
      "size": {
        "0": 315,
        "1": 314
      },
      "flags": {},
      "order": 7,
      "mode": 0,
      "inputs": [],
      "outputs": [
        {
          "name": "IMAGE",
          "type": "IMAGE",
          "links": [
            21
          ],
          "shape": 3,
          "label": "图像"
        },
        {
          "name": "MASK",
          "type": "MASK",
          "links": null,
          "shape": 3,
          "label": "遮罩"
        }
      ],
      "properties": {
        "Node name for S&R": "LoadImage"
      },
      "widgets_values": [
        "ComfyUI_00120_.png",
        "image"
      ]
    }
  ],
  "links": [
    [
      2,
      5,
      0,
      3,
      3,
      "LATENT"
    ],
    [
      4,
      6,
      0,
      3,
      1,
      "CONDITIONING"
    ],
    [
      6,
      7,
      0,
      3,
      2,
      "CONDITIONING"
    ],
    [
      7,
      3,
      0,
      8,
      0,
      "LATENT"
    ],
    [
      9,
      8,
      0,
      9,
      0,
      "IMAGE"
    ],
    [
      13,
      14,
      0,
      6,
      0,
      "CLIP"
    ],
    [
      14,
      14,
      0,
      7,
      0,
      "CLIP"
    ],
    [
      15,
      15,
      0,
      8,
      1,
      "VAE"
    ],
    [
      16,
      10,
      0,
      16,
      0,
      "MODEL"
    ],
    [
      17,
      16,
      0,
      3,
      0,
      "MODEL"
    ],
    [
      18,
      17,
      0,
      16,
      1,
      "PULIDFLUX"
    ],
    [
      19,
      18,
      0,
      16,
      2,
      "EVA_CLIP"
    ],
    [
      20,
      19,
      0,
      16,
      3,
      "FACEANALYSIS"
    ],
    [
      21,
      20,
      0,
      16,
      4,
      "IMAGE"
    ]
  ],
  "groups": [
    {
      "title": "Pulid-flux",
      "bounding": [
        39,
        -648,
        765,
        713
      ],
      "color": "#8A8",
      "font_size": 24,
      "flags": {}
    },
    {
      "title": "生图模块",
      "bounding": [
        42,
        114,
        1849,
        611
      ],
      "color": "#3f789e",
      "font_size": 24,
      "flags": {}
    }
  ],
  "config": {},
  "extra": {
    "ds": {
      "scale": 0.7247295000000007,
      "offset": [
        770.8270385419872,
        668.1106045802637
      ]
    }
  },
  "version": 0.4
}